gradio_markdowntooltip/__init__.py
gradio_markdowntooltip/markdowntooltip.py
gradio_markdowntooltip/markdowntooltip.pyi
gradio_markdowntooltip/templates/component/Index-D-NddAVo.js
gradio_markdowntooltip/templates/component/_basePickBy-B9VKJyMF.js
gradio_markdowntooltip/templates/component/_baseUniq-xl0sditF.js
gradio_markdowntooltip/templates/component/arc-CQAqmrCp.js
gradio_markdowntooltip/templates/component/architectureDiagram-W76B3OCA-CDsCpjlW.js
gradio_markdowntooltip/templates/component/auto-render-BwaQGe8P.js
gradio_markdowntooltip/templates/component/blockDiagram-QIGZ2CNN-CgRFeHty.js
gradio_markdowntooltip/templates/component/c4Diagram-FPNF74CW-DLIWYs7u.js
gradio_markdowntooltip/templates/component/channel-Ca8IkiVh.js
gradio_markdowntooltip/templates/component/chunk-4BX2VUAB-CHZmW6Kc.js
gradio_markdowntooltip/templates/component/chunk-55IACEB6-DLn7xMfg.js
gradio_markdowntooltip/templates/component/chunk-FMBD7UC4-DEZYaZih.js
gradio_markdowntooltip/templates/component/chunk-K7UQS3LO-kEpfK7kV.js
gradio_markdowntooltip/templates/component/chunk-QN33PNHL-ilpXy3rp.js
gradio_markdowntooltip/templates/component/chunk-QZHKN3VN-DZWL2VgW.js
gradio_markdowntooltip/templates/component/chunk-TVAH2DTR-C3y214Te.js
gradio_markdowntooltip/templates/component/chunk-TZMSLE5B-Cn5dUQX0.js
gradio_markdowntooltip/templates/component/classDiagram-KNZD7YFC-DOG7_vKN.js
gradio_markdowntooltip/templates/component/classDiagram-v2-RKCZMP56-DOG7_vKN.js
gradio_markdowntooltip/templates/component/clone-C970XNbn.js
gradio_markdowntooltip/templates/component/cose-bilkent-S5V4N54A-D_Q6-nvr.js
gradio_markdowntooltip/templates/component/cytoscape.esm-ZmItrg9y.js
gradio_markdowntooltip/templates/component/dagre-5GWH7T2D-O-ZVFxCa.js
gradio_markdowntooltip/templates/component/defaultLocale-D7EN2tov.js
gradio_markdowntooltip/templates/component/diagram-N5W7TBWH-BJR4Jn8D.js
gradio_markdowntooltip/templates/component/diagram-QEK2KX5R-BAxS6Sjg.js
gradio_markdowntooltip-0.0.1.dist-info/METADATA
gradio_markdowntooltip-0.0.1.dist-info/WHEEL
gradio_markdowntooltip-0.0.1.dist-info/RECORD
